[
    {
        "freeze": [],
        "unit": [
            0
        ],
        "time": 1.0,
        "data": 1.0,
        "memory": 1.0,
        "__debug_max_time_in_s": 0.77525,
        "__debug_max_data_in_bytes": 0.03675,
        "__debug_max_mem_in_gb": 0.78141
    },
    {
        "freeze": [
            10,
            11,
            12,
            13,
            14,
            15,
            16,
            17,
            18,
            19
        ],
        "unit": [
            10
        ],
        "time": 0.86845,
        "data": 0.08152,
        "memory": 0.99021
    },
    {
        "freeze": [
            6,
            7,
            8,
            9,
            10,
            11,
            12,
            13,
            14,
            15,
            16,
            17,
            18,
            19
        ],
        "unit": [
            6
        ],
        "time": 0.81409,
        "data": 0.01862,
        "memory": 0.97674
    },
    {
        "freeze": [
            4,
            5,
            6,
            7,
            8,
            9,
            10,
            11,
            12,
            13,
            14,
            15,
            16,
            17,
            18,
            19
        ],
        "unit": [
            4
        ],
        "time": 0.78885,
        "data": 0.00779,
        "memory": 1.01652
    },
    {
        "freeze": [
            5,
            6,
            7,
            8,
            9,
            10,
            11,
            12,
            13,
            14,
            15,
            16,
            17,
            18,
            19
        ],
        "unit": [
            5
        ],
        "time": 0.78567,
        "data": 0.01215,
        "memory": 1.00536
    },
    {
        "freeze": [
            0,
            1,
            4,
            5,
            6,
            7,
            8,
            9,
            10,
            11,
            12,
            13,
            14,
            15,
            16,
            17,
            18,
            19
        ],
        "unit": [
            2
        ],
        "time": 0.72877,
        "data": 0.00628,
        "memory": 0.97168
    },
    {
        "freeze": [
            3,
            4,
            5,
            6,
            7,
            8,
            9,
            10,
            11,
            12,
            13,
            14,
            15,
            16,
            17,
            18,
            19
        ],
        "unit": [
            3
        ],
        "time": 0.70891,
        "data": 0.00394,
        "memory": 1.0067
    },
    {
        "freeze": [
            0,
            1,
            3,
            4,
            5,
            6,
            7,
            8,
            9,
            10,
            11,
            12,
            13,
            14,
            15,
            16,
            17,
            18,
            19
        ],
        "unit": [
            1
        ],
        "time": 0.69138,
        "data": 0.00243,
        "memory": 0.9815
    },
    {
        "freeze": [
            2,
            3,
            4,
            5,
            6,
            7,
            8,
            9,
            10,
            11,
            12,
            13,
            14,
            15,
            16,
            17,
            18,
            19
        ],
        "unit": [
            2
        ],
        "time": 0.66872,
        "data": 0.00151,
        "memory": 1.02444
    },
    {
        "freeze": [
            0,
            2,
            3,
            4,
            5,
            6,
            7,
            8,
            9,
            10,
            11,
            12,
            13,
            14,
            15,
            16,
            17,
            18,
            19
        ],
        "unit": [
            1
        ],
        "time": 0.65551,
        "data": 0.00111,
        "memory": 1.0208
    },
    {
        "freeze": [
            1,
            2,
            3,
            4,
            5,
            6,
            7,
            8,
            9,
            10,
            11,
            12,
            13,
            14,
            15,
            16,
            17,
            18,
            19
        ],
        "unit": [
            1
        ],
        "time": 0.65057,
        "data": 0.0004,
        "memory": 1.01922
    },
    {
        "freeze": [
            0,
            1,
            2,
            6,
            7,
            8,
            9,
            10,
            11,
            12,
            13,
            14,
            15,
            16,
            17,
            18,
            19
        ],
        "unit": [
            3
        ],
        "time": 0.64897,
        "data": 0.01468,
        "memory": 0.83917
    },
    {
        "freeze": [
            0,
            1,
            2,
            4,
            5,
            6,
            7,
            8,
            9,
            10,
            11,
            12,
            13,
            14,
            15,
            16,
            17,
            18,
            19
        ],
        "unit": [
            1
        ],
        "time": 0.60131,
        "data": 0.00385,
        "memory": 0.8706
    },
    {
        "freeze": [
            0,
            1,
            2,
            3,
            8,
            9,
            10,
            11,
            12,
            13,
            14,
            15,
            16,
            17,
            18,
            19
        ],
        "unit": [
            4
        ],
        "time": 0.48517,
        "data": 0.02647,
        "memory": 0.69613
    },
    {
        "freeze": [
            0,
            1,
            2,
            3,
            6,
            7,
            8,
            9,
            10,
            11,
            12,
            13,
            14,
            15,
            16,
            17,
            18,
            19
        ],
        "unit": [
            2
        ],
        "time": 0.46282,
        "data": 0.01083,
        "memory": 0.71787
    },
    {
        "freeze": [
            0,
            1,
            2,
            3,
            5,
            6,
            7,
            8,
            9,
            10,
            11,
            12,
            13,
            14,
            15,
            16,
            17,
            18,
            19
        ],
        "unit": [
            1
        ],
        "time": 0.44593,
        "data": 0.00436,
        "memory": 0.69894
    },
    {
        "freeze": [
            0,
            1,
            2,
            3,
            4,
            10,
            11,
            12,
            13,
            14,
            15,
            16,
            17,
            18,
            19
        ],
        "unit": [
            5
        ],
        "time": 0.43158,
        "data": 0.06937,
        "memory": 0.58167
    },
    {
        "freeze": [
            0,
            1,
            2,
            3,
            4,
            5,
            6,
            7,
            8,
            9
        ],
        "unit": [
            10
        ],
        "time": 0.42933,
        "data": 0.91848,
        "memory": 0.37469
    },
    {
        "freeze": [
            0,
            1,
            2,
            3,
            4,
            5,
            12,
            13,
            14,
            15,
            16,
            17,
            18,
            19
        ],
        "unit": [
            6
        ],
        "time": 0.41905,
        "data": 0.1183,
        "memory": 0.52083
    },
    {
        "freeze": [
            0,
            1,
            2,
            3,
            4,
            5,
            8,
            9,
            10,
            11,
            12,
            13,
            14,
            15,
            16,
            17,
            18,
            19
        ],
        "unit": [
            2
        ],
        "time": 0.39535,
        "data": 0.01564,
        "memory": 0.50744
    },
    {
        "freeze": [
            0,
            1,
            2,
            3,
            4,
            6,
            7,
            8,
            9,
            10,
            11,
            12,
            13,
            14,
            15,
            16,
            17,
            18,
            19
        ],
        "unit": [
            1
        ],
        "time": 0.39124,
        "data": 0.00647,
        "memory": 0.56238
    },
    {
        "freeze": [
            0,
            1,
            2,
            3,
            4,
            5,
            9,
            10,
            11,
            12,
            13,
            14,
            15,
            16,
            17,
            18,
            19
        ],
        "unit": [
            3
        ],
        "time": 0.38125,
        "data": 0.03927,
        "memory": 0.53858
    },
    {
        "freeze": [
            0,
            1,
            2,
            3,
            4,
            5,
            7,
            8,
            9,
            10,
            11,
            12,
            13,
            14,
            15,
            16,
            17,
            18,
            19
        ],
        "unit": [
            1
        ],
        "time": 0.36407,
        "data": 0.00647,
        "memory": 0.54235
    },
    {
        "freeze": [
            0,
            1,
            2,
            3,
            4,
            5,
            6,
            7,
            12,
            13,
            14,
            15,
            16,
            17,
            18,
            19
        ],
        "unit": [
            4
        ],
        "time": 0.35536,
        "data": 0.10266,
        "memory": 0.46432
    },
    {
        "freeze": [
            0,
            1,
            2,
            3,
            4,
            5,
            6,
            7,
            8,
            9,
            15,
            16,
            17,
            18,
            19
        ],
        "unit": [
            5
        ],
        "time": 0.34467,
        "data": 0.22598,
        "memory": 0.37066
    },
    {
        "freeze": [
            0,
            1,
            2,
            3,
            4,
            5,
            6,
            7,
            8,
            9,
            10,
            11,
            18,
            19
        ],
        "unit": [
            6
        ],
        "time": 0.33995,
        "data": 0.67808,
        "memory": 0.3059
    },
    {
        "freeze": [
            0,
            1,
            2,
            3,
            4,
            5,
            6,
            7,
            10,
            11,
            12,
            13,
            14,
            15,
            16,
            17,
            18,
            19
        ],
        "unit": [
            2
        ],
        "time": 0.33175,
        "data": 0.04726,
        "memory": 0.43433
    },
    {
        "freeze": [
            0,
            1,
            2,
            3,
            4,
            5,
            6,
            8,
            9,
            10,
            11,
            12,
            13,
            14,
            15,
            16,
            17,
            18,
            19
        ],
        "unit": [
            1
        ],
        "time": 0.32425,
        "data": 0.00917,
        "memory": 0.47296
    },
    {
        "freeze": [
            0,
            1,
            2,
            3,
            4,
            5,
            6,
            7,
            8,
            12,
            13,
            14,
            15,
            16,
            17,
            18,
            19
        ],
        "unit": [
            3
        ],
        "time": 0.32251,
        "data": 0.07903,
        "memory": 0.41918
    },
    {
        "freeze": [
            0,
            1,
            2,
            3,
            4,
            5,
            6,
            7,
            9,
            10,
            11,
            12,
            13,
            14,
            15,
            16,
            17,
            18,
            19
        ],
        "unit": [
            1
        ],
        "time": 0.32036,
        "data": 0.02363,
        "memory": 0.43012
    },
    {
        "freeze": [
            0,
            1,
            2,
            3,
            4,
            5,
            6,
            7,
            8,
            10,
            11,
            12,
            13,
            14,
            15,
            16,
            17,
            18,
            19
        ],
        "unit": [
            1
        ],
        "time": 0.30789,
        "data": 0.02363,
        "memory": 0.40574
    },
    {
        "freeze": [
            0,
            1,
            2,
            3,
            4,
            5,
            6,
            7,
            8,
            9,
            12,
            13,
            14,
            15,
            16,
            17,
            18,
            19
        ],
        "unit": [
            2
        ],
        "time": 0.30242,
        "data": 0.0554,
        "memory": 0.36354
    },
    {
        "freeze": [
            0,
            1,
            2,
            3,
            4,
            5,
            6,
            7,
            8,
            9,
            10,
            11,
            16,
            17,
            18,
            19
        ],
        "unit": [
            4
        ],
        "time": 0.2937,
        "data": 0.30989,
        "memory": 0.29261
    },
    {
        "freeze": [
            0,
            1,
            2,
            3,
            4,
            5,
            6,
            7,
            8,
            9,
            11,
            12,
            13,
            14,
            15,
            16,
            17,
            18,
            19
        ],
        "unit": [
            1
        ],
        "time": 0.29056,
        "data": 0.02363,
        "memory": 0.37093
    },
    {
        "freeze": [
            0,
            1,
            2,
            3,
            4,
            5,
            6,
            7,
            8,
            9,
            10,
            12,
            13,
            14,
            15,
            16,
            17,
            18,
            19
        ],
        "unit": [
            1
        ],
        "time": 0.27523,
        "data": 0.03177,
        "memory": 0.32923
    },
    {
        "freeze": [
            0,
            1,
            2,
            3,
            4,
            5,
            6,
            7,
            8,
            9,
            10,
            11,
            15,
            16,
            17,
            18,
            19
        ],
        "unit": [
            3
        ],
        "time": 0.27095,
        "data": 0.17058,
        "memory": 0.31072
    },
    {
        "freeze": [
            0,
            1,
            2,
            3,
            4,
            5,
            6,
            7,
            8,
            9,
            10,
            11,
            14,
            15,
            16,
            17,
            18,
            19
        ],
        "unit": [
            2
        ],
        "time": 0.27035,
        "data": 0.10298,
        "memory": 0.2992
    },
    {
        "freeze": [
            0,
            1,
            2,
            3,
            4,
            5,
            6,
            7,
            8,
            9,
            10,
            11,
            12,
            14,
            15,
            16,
            17,
            18,
            19
        ],
        "unit": [
            1
        ],
        "time": 0.25447,
        "data": 0.05149,
        "memory": 0.26763
    },
    {
        "freeze": [
            0,
            1,
            2,
            3,
            4,
            5,
            6,
            7,
            8,
            9,
            10,
            11,
            13,
            14,
            15,
            16,
            17,
            18,
            19
        ],
        "unit": [
            1
        ],
        "time": 0.25249,
        "data": 0.05149,
        "memory": 0.29012
    },
    {
        "freeze": [
            0,
            1,
            2,
            3,
            4,
            5,
            6,
            7,
            8,
            9,
            10,
            11,
            12,
            13,
            14,
            18,
            19
        ],
        "unit": [
            3
        ],
        "time": 0.24005,
        "data": 0.5075,
        "memory": 0.19813
    },
    {
        "freeze": [
            0,
            1,
            2,
            3,
            4,
            5,
            6,
            7,
            8,
            9,
            10,
            11,
            12,
            13,
            14,
            15
        ],
        "unit": [
            4
        ],
        "time": 0.234,
        "data": 0.55319,
        "memory": 0.18505
    },
    {
        "freeze": [
            0,
            1,
            2,
            3,
            4,
            5,
            6,
            7,
            8,
            9,
            10,
            11,
            12,
            13,
            14
        ],
        "unit": [
            5
        ],
        "time": 0.22793,
        "data": 0.6925,
        "memory": 0.19397
    },
    {
        "freeze": [
            0,
            1,
            2,
            3,
            4,
            5,
            6,
            7,
            8,
            9,
            10,
            11,
            12,
            13,
            16,
            17,
            18,
            19
        ],
        "unit": [
            2
        ],
        "time": 0.2131,
        "data": 0.2069,
        "memory": 0.21853
    },
    {
        "freeze": [
            0,
            1,
            2,
            3,
            4,
            5,
            6,
            7,
            8,
            9,
            10,
            11,
            12,
            13,
            14,
            15,
            18,
            19
        ],
        "unit": [
            2
        ],
        "time": 0.19899,
        "data": 0.36819,
        "memory": 0.17723
    },
    {
        "freeze": [
            0,
            1,
            2,
            3,
            4,
            5,
            6,
            7,
            8,
            9,
            10,
            11,
            12,
            13,
            15,
            16,
            17,
            18,
            19
        ],
        "unit": [
            1
        ],
        "time": 0.19821,
        "data": 0.06759,
        "memory": 0.20902
    },
    {
        "freeze": [
            0,
            1,
            2,
            3,
            4,
            5,
            6,
            7,
            8,
            9,
            10,
            11,
            12,
            13,
            14,
            16,
            17,
            18,
            19
        ],
        "unit": [
            1
        ],
        "time": 0.193,
        "data": 0.13931,
        "memory": 0.18841
    },
    {
        "freeze": [
            0,
            1,
            2,
            3,
            4,
            5,
            6,
            7,
            8,
            9,
            10,
            11,
            12,
            13,
            14,
            15,
            16,
            18,
            19
        ],
        "unit": [
            1
        ],
        "time": 0.1918,
        "data": 0.22888,
        "memory": 0.17547
    },
    {
        "freeze": [
            0,
            1,
            2,
            3,
            4,
            5,
            6,
            7,
            8,
            9,
            10,
            11,
            12,
            13,
            14,
            15,
            17,
            18,
            19
        ],
        "unit": [
            1
        ],
        "time": 0.18425,
        "data": 0.13931,
        "memory": 0.17306
    },
    {
        "freeze": [
            0,
            1,
            2,
            3,
            4,
            5,
            6,
            7,
            8,
            9,
            10,
            11,
            12,
            13,
            14,
            15,
            16,
            17
        ],
        "unit": [
            2,
            3,
            6
        ],
        "time": 0.1649,
        "data": 0.185,
        "memory": 0.16591
    },
    {
        "freeze": [
            0,
            1,
            2,
            3,
            4,
            5,
            6,
            7,
            8,
            9,
            10,
            11,
            12,
            13,
            14,
            15,
            16,
            17,
            18
        ],
        "unit": [
            1
        ],
        "time": 0.16115,
        "data": 0.00558,
        "memory": 0.161
    },
    {
        "freeze": [
            0,
            1,
            2,
            3,
            4,
            5,
            6,
            7,
            8,
            9,
            10,
            11,
            12,
            13,
            14,
            15,
            16,
            17,
            19
        ],
        "unit": [
            1
        ],
        "time": 0.15289,
        "data": 0.17942,
        "memory": 0.16069
    }
]